bmp_280/__init__.py
bmp_280/bmp_280.py
bmp_280-0.1.2.data/scripts/run-bmp280
bmp_280-0.1.2.dist-info/LICENSE
bmp_280-0.1.2.dist-info/METADATA
bmp_280-0.1.2.dist-info/WHEEL
bmp_280-0.1.2.dist-info/top_level.txt
bmp_280-0.1.2.dist-info/RECORD
