Metadata-Version: 2.1
Name: bmp-280
Version: 0.1.2
Summary: Python3 I2C Driver & Application for BMP280 Pressure Sensor
Home-page: https://github.com/feyzikesim/bmp280
Author: Feyzi Kesim
Author-email: feyzikesim@gmail.com
License: UNKNOWN
Platform: UNKNOWN
Classifier: Programming Language :: Python :: 3
Classifier: License :: OSI Approved :: MIT License
Classifier: Operating System :: OS Independent
Requires-Python: >=3.6
